Workbook
Name Churn: Assumptions!$B$5
Name CogsShare: Assumptions!$B$6
Name NewSeats: Assumptions!$B$3
Name Opex: Assumptions!$B$7
Name Price: Assumptions!$B$4
Name StartSeats: Assumptions!$B$2

Sheet Assumptions
A1: Assumption | B1: Value
A2: Starting seats | B2: 120
A3: New seats per month | B3: 15
A4: Price per seat | B4: 49
A5: Monthly churn | B5: 0.02
A6: COGS share | B6: 0.18
A7: Monthly opex | B7: 85000

Sheet Revenue
A1: Month | B1: Seats | C1: MRR | D1: COGS | E1: Gross margin
A2: 1 | B2: =StartSeats -> 120 | C2: =B2*Price*(1-Churn) -> 5762.4 | D2: =C2*CogsShare -> 1037.232 | E2: =C2-D2 -> 4725.168
A3: 2 | B3: =B2+NewSeats -> 135 | C3: =B3*Price*(1-Churn) -> 6482.7 | D3: =C3*CogsShare -> 1166.886 | E3: =C3-D3 -> 5315.814
A4: 3 | B4: =B3+NewSeats -> 150 | C4: =B4*Price*(1-Churn) -> 7203 | D4: =C4*CogsShare -> 1296.54 | E4: =C4-D4 -> 5906.46
A5: 4 | B5: =B4+NewSeats -> 165 | C5: =B5*Price*(1-Churn) -> 7923.3 | D5: =C5*CogsShare -> 1426.194 | E5: =C5-D5 -> 6497.106
A6: 5 | B6: =B5+NewSeats -> 180 | C6: =B6*Price*(1-Churn) -> 8643.6 | D6: =C6*CogsShare -> 1555.848 | E6: =C6-D6 -> 7087.752
A7: 6 | B7: =B6+NewSeats -> 195 | C7: =B7*Price*(1-Churn) -> 9363.9 | D7: =C7*CogsShare -> 1685.502 | E7: =C7-D7 -> 7678.398
A8: 7 | B8: =B7+NewSeats -> 210 | C8: =B8*Price*(1-Churn) -> 10084.2 | D8: =C8*CogsShare -> 1815.156 | E8: =C8-D8 -> 8269.044
A9: 8 | B9: =B8+NewSeats -> 225 | C9: =B9*Price*(1-Churn) -> 10804.5 | D9: =C9*CogsShare -> 1944.81 | E9: =C9-D9 -> 8859.69
A10: 9 | B10: =B9+NewSeats -> 240 | C10: =B10*Price*(1-Churn) -> 11524.8 | D10: =C10*CogsShare -> 2074.464 | E10: =C10-D10 -> 9450.336
A11: 10 | B11: =B10+NewSeats -> 255 | C11: =B11*Price*(1-Churn) -> 12245.1 | D11: =C11*CogsShare -> 2204.118 | E11: =C11-D11 -> 10040.982
A12: 11 | B12: =B11+NewSeats -> 270 | C12: =B12*Price*(1-Churn) -> 12965.4 | D12: =C12*CogsShare -> 2333.772 | E12: =C12-D12 -> 10631.628
A13: 12 | B13: =B12+NewSeats -> 285 | C13: =B13*Price*(1-Churn) -> 13685.7 | D13: =C13*CogsShare -> 2463.426 | E13: =C13-D13 -> 11222.274
A14: 13 | B14: =B13+NewSeats -> 300 | C14: =B14*Price*(1-Churn) -> 14406 | D14: =C14*CogsShare -> 2593.08 | E14: =C14-D14 -> 11812.92
... A25: 24 | B25: =B24+NewSeats -> 465 | C25: =B25*Price*(1-Churn) -> 22329.3 | D25: =C25*CogsShare -> 4019.274 | E25: =C25-D25 -> 18310.026

Sheet P&L
B1: Year 1 | C1: Year 2
A2: Revenue | B2: =SUM(Revenue!C2:C13) -> 116688.6 | C2: =SUM(Revenue!C14:C25) -> 220411.8
A3: COGS | B3: =SUM(Revenue!D2:D13) -> 21003.948 | C3: =SUM(Revenue!D14:D25) -> 39674.124
A4: Gross margin | B4: =B2-B3 -> 95684.652 | C4: =C2-C3 -> 180737.68
A5: Operating expenses | B5: =Opex*12 -> 1020000 | C5: =Opex*12 -> 1020000
A6: EBITDA | B6: =B4-B5 -> -924315.35 | C6: =C4-C5 -> -839262.32

Sheet Summary
A1: Brightwell Analytics: summary
A2: Year 1 revenue | B2: ='P&L'!B2 -> 116688.6
A3: Year 2 revenue | B3: ='P&L'!C2 -> 220411.8
A4: Year 2 EBITDA | B4: ='P&L'!C6 -> -839262.32
A5: Seats at month 24 | B5: =Revenue!B25 -> 465
A6: Prepared on | B6: =TODAY() -> 46023
